README.md
setup.py
guppi/__init__.py
guppi.egg-info/PKG-INFO
guppi.egg-info/SOURCES.txt
guppi.egg-info/dependency_links.txt
guppi.egg-info/entry_points.txt
guppi.egg-info/namespace_packages.txt
guppi.egg-info/not-zip-safe
guppi.egg-info/requires.txt
guppi.egg-info/top_level.txt